MiaoSQL/Exception.py
MiaoSQL/__init__.py
MiaoSQL/miaosql.py
MiaoSQL-0.0.4.dist-info/METADATA
MiaoSQL-0.0.4.dist-info/WHEEL
MiaoSQL-0.0.4.dist-info/top_level.txt
MiaoSQL-0.0.4.dist-info/RECORD
